LICENSE
giant_faqs/__init__.py
giant_faqs/admin.py
giant_faqs/apps.py
giant_faqs/cms_apps.py
giant_faqs/cms_plugins.py
giant_faqs/forms.py
giant_faqs/migrations/0001_initial.py
giant_faqs/migrations/0002_faqblock.py
giant_faqs/migrations/0003_auto_20220622_0727.py
giant_faqs/migrations/__init__.py
giant_faqs/models.py
giant_faqs/sitemaps.py
giant_faqs/templates/base.html
giant_faqs/templates/faqs/_components/faq.html
giant_faqs/templates/faqs/index.html
giant_faqs/templates/faqs/plugin.html
giant_faqs/tests/__init__.py
giant_faqs/tests/conftest.py
giant_faqs/tests/test_cms_apps.py
giant_faqs/tests/test_forms.py
giant_faqs/tests/test_models.py
giant_faqs/tests/test_views.py
giant_faqs/tests/urls.py
giant_faqs/urls.py
giant_faqs/views.py
giant_faqs-0.2.1.dist-info/LICENSE
giant_faqs-0.2.1.dist-info/WHEEL
giant_faqs-0.2.1.dist-info/METADATA
giant_faqs-0.2.1.dist-info/RECORD
