Metadata-Version: 2.1
Name: giant-faqs
Version: 0.2.1
Summary: A small reusable package that adds a FAQ app to a project
Home-page: https://github.com/giantmade/giant-faqs
License: MIT
Keywords: giant_faqs,app
Author: Domchap90
Author-email: dominic.chaple@giantdigital.co.uk
Requires-Python: >=3.9,<4.0
Classifier: Environment :: Console
Classifier: License :: OSI Approved :: MIT License
Classifier: Operating System :: OS Independent
Classifier: Programming Language :: Python :: 3
Classifier: Programming Language :: Python :: 3.10
Classifier: Programming Language :: Python :: 3.9
Classifier: Topic :: Software Development :: Documentation
Classifier: Topic :: Software Development :: Libraries :: Python Modules
Requires-Dist: giant-mixins
Requires-Dist: giant-plugins
Project-URL: Repository, https://github.com/giantmade/giant-faqs
